LICENSE.md
README.md
setup.cfg
setup.py
pylag/__init__.py
pylag/absorber.py
pylag/binning.py
pylag/bispectrum.py
pylag/cepstrum.py
pylag/coherence.py
pylag/continuum.py
pylag/correlation.py
pylag/covariance.py
pylag/cross_spectrum.py
pylag/dcf.py
pylag/entresponse.py
pylag/event_list.py
pylag/fit.py
pylag/fits_spec_model.py
pylag/flux_histogram.py
pylag/fvar.py
pylag/gaussian_process.py
pylag/gaussian_process_celerite.py
pylag/lag_energy_spectrum.py
pylag/lag_frequency_spectrum.py
pylag/lens_lag.py
pylag/lightcurve.py
pylag/math_functions.py
pylag/mlcovariance.py
pylag/mlfit.py
pylag/model.py
pylag/periodogram.py
pylag/plotter.py
pylag/response.py
pylag/reverb_model.py
pylag/rms.py
pylag/simulator.py
pylag/time.py
pylag/util.py
pylag/xspec_model.py
pylag.egg-info/PKG-INFO
pylag.egg-info/SOURCES.txt
pylag.egg-info/dependency_links.txt
pylag.egg-info/requires.txt
pylag.egg-info/top_level.txt